epsg_cache/__init__.py
epsg_cache/apps.py
epsg_cache/exceptions.py
epsg_cache/models.py
epsg_cache/registry.py
epsg_cache/settings.py
epsg_cache/utils.py
django_epsg_cache-0.2.1.dist-info/LICENSE
django_epsg_cache-0.2.1.dist-info/METADATA
django_epsg_cache-0.2.1.dist-info/WHEEL
django_epsg_cache-0.2.1.dist-info/top_level.txt
django_epsg_cache-0.2.1.dist-info/RECORD
