Metadata-Version: 2.1
Name: django-epsg-cache
Version: 0.2.1
Summary: An django app to fetch and cache EPSG Datasets from http://epsg-registry.org
Home-page: https://github.com/mrmap-community/django-epsg-cache
Author: mrmap-commuity
Author-email: jonas.kiefer@live.com
License: MIT
Platform: UNKNOWN
Classifier: Development Status :: 5 - Production/Stable
Classifier: Intended Audience :: Developers
Classifier: Natural Language :: English
Classifier: Programming Language :: Python :: 3.8
Classifier: Programming Language :: Python :: 3.9
Classifier: Programming Language :: Python :: 3.10
Classifier: Programming Language :: Python :: 3.11
Classifier: Topic :: Internet :: WWW/HTTP
Classifier: Environment :: Web Environment
Classifier: Framework :: Django
Classifier: Topic :: Software Development :: Libraries
Classifier: License :: OSI Approved :: MIT License
Classifier: Operating System :: OS Independent
Requires-Python: >=3.8
License-File: LICENSE
Requires-Dist: django (>=3.2)
Requires-Dist: lxml (>=5.0.0)
Requires-Dist: requests (>=2.23.0)
